aws_session_daemon.py
aws_session_daemon-0.6.0.dist-info/LICENSE.txt
aws_session_daemon-0.6.0.dist-info/METADATA
aws_session_daemon-0.6.0.dist-info/WHEEL
aws_session_daemon-0.6.0.dist-info/entry_points.txt
aws_session_daemon-0.6.0.dist-info/RECORD
