Metadata-Version: 2.1
Name: aws-session-daemon
Version: 0.6.0
Summary: AWS session token refreshing daemon
Home-page: https://github.com/meeuw/aws-session-daemon
Keywords: AWS,MFA,keyring,keychain,yubikey
Author: Dick Marinus
Author-email: dick@mrns.nl
Requires-Python: >=3.7,<4.0
Classifier: Programming Language :: Python :: 3
Classifier: Programming Language :: Python :: 3.7
Classifier: Programming Language :: Python :: 3.8
Classifier: Programming Language :: Python :: 3.9
Classifier: Programming Language :: Python :: 3.10
Classifier: Programming Language :: Python :: 3.11
Requires-Dist: aws_credential_process (>=0.19)
Requires-Dist: click (>=8.1)
Requires-Dist: pyscard (<2.0.4)
Requires-Dist: toml (>=0.10.2,<0.11.0)
Project-URL: Repository, https://github.com/meeuw/aws-session-daemon
